django4django/__init__.py
django4django/admin.py
django4django/apps.py
django4django/models.py
django4django/tests.py
django4django/version.txt
django4django/views.py
django4django/migrations/__init__.py
django4django-0.0.2.dist-info/LICENSE
django4django-0.0.2.dist-info/METADATA
django4django-0.0.2.dist-info/WHEEL
django4django-0.0.2.dist-info/top_level.txt
django4django-0.0.2.dist-info/RECORD
